good_password_generator/__init__.py
good_password_generator/__main__.py
good_password_generator/password_generator.py
good_password_generator-0.0.7.dist-info/LICENSE
good_password_generator-0.0.7.dist-info/METADATA
good_password_generator-0.0.7.dist-info/WHEEL
good_password_generator-0.0.7.dist-info/top_level.txt
good_password_generator-0.0.7.dist-info/RECORD
